{
    "matrix_probe_in_cam_coord": [
        [
            -0.9663091722203377,
            0.04139949892723436,
            0.2540328033373241,
            -0.5659460575264186
        ],
        [
            -0.19711303043147085,
            -0.7536995224610599,
            -0.6269637015618146,
            0.7813678963644051
        ],
        [
            0.16550841947456227,
            -0.6559139511632176,
            0.7364671423441023,
            -11.545225331282769
        ],
        [
            0.0,
            0.0,
            0.0,
            1.0
        ]
    ],
    "matrix_probe_in_world_coord": [
        [
            -0.0947300133147342,
            -0.6924779494021178,
            -0.7151926412996906,
            0.0
        ],
        [
            0.9845379773226617,
            0.04116689108590497,
            -0.17026525860469266,
            0.0
        ],
        [
            0.14734719470282395,
            -0.7202635466759085,
            0.6778710995042118,
            5.494297504425049
        ],
        [
            0.0,
            0.0,
            0.0,
            1.0
        ]
    ],
    "intrinsic_matrix_camera": [
        [
            1.3888888888888888,
            0.0,
            -0.5
        ],
        [
            0.0,
            -1.3888888888888888,
            -0.5
        ],
        [
            0.0,
            0.0,
            -1.0
        ]
    ],
    "extrinsic_matrix_camera": [
        [
            -0.11881215096840966,
            0.9889926454954963,
            -0.08818854765829374,
            -1.8581650257110596
        ],
        [
            -0.9929167501771029,
            -0.11834259365541597,
            0.01055261790501684,
            -0.3476358652114868
        ],
        [
            3.819900701515887e-11,
            0.0888176653753544,
            0.9960479016178245,
            16.924495697021484
        ],
        [
            0.0,
            0.0,
            0.0,
            1.0
        ]
    ],
    "matrix_probe_in_cam_coord_pre": [
        [
            -0.6657202243804932,
            0.06342942267656326,
            0.15268561244010925,
            -0.25441327691078186
        ],
        [
            -0.09285868704319,
            -0.5017998218536377,
            -0.5533653497695923,
            0.8150500059127808
        ],
        [
            0.19930584728717804,
            -0.4024275541305542,
            0.8321808576583862,
            -11.714522361755371
        ],
        [
            0.0,
            0.0,
            0.0,
            1.0
        ]
    ]
}